chaitin_rpa/__init__.py
chaitin_rpa/api/cards.py
chaitin_rpa/api/chaitin.py
chaitin_rpa/api/feishu.py
chaitin_rpa/cli.py
chaitin_rpa/config.py
chaitin_rpa/database.py
chaitin_rpa/log.py
chaitin_rpa/tables.py
chaitin_rpa/utils.py
chaitin_rpa-0.0.1.dist-info/METADATA
chaitin_rpa-0.0.1.dist-info/WHEEL
chaitin_rpa-0.0.1.dist-info/entry_points.txt
chaitin_rpa-0.0.1.dist-info/RECORD
